{
    "W1": {
        "2.4G": {
            "SDIO": {
                "11N": {
                    "WPA2": {
                        "20MHZ": {
                            "1X1": {
                                "UL": 42.8,
                                "DL": 42.8
                            }
                        },
                        "40MHZ": {
                            "1X1": {
                                "UL": 85.5,
                                "DL": 85.5
                            }
                        }
                    }
                }
            }
        },
        "5G": {
            "SDIO": {
                "11AC": {
                    "WPA2": {
                        "80MHZ": {
                            "1X1": {
                                "UL": 209,
                                "DL": 237.5
                            }
                        }
                    }
                }
            }
        }
    },
    "W2": {
        "2.4G": {
            "SDIO": {
                "11N": {
                    "WPA2": {
                        "20MHZ": {
                            "2X2": {
                                "UL": 85.5,
                                "DL": 85.5
                            }
                        },
                        "40MHZ": {
                            "2X2": {
                                "UL": 162.5,
                                "DL": 162.5
                            }
                        }
                    }
                },
                "11AX": {
                    "WPA2": {
                        "20MHZ": {
                            "2X2": {
                                "UL": 162.5,
                                "DL": 162.5
                            }
                        },
                        "40MHZ": {
                            "2X2": {
                                "UL": 325,
                                "DL": 325
                            }
                        }
                    }
                }
            },
            "USB": {
                "11N": {
                    "WPA2": {
                        "20MHZ": {
                            "2X2": {
                                "UL": 85.5,
                                "DL": 85.5
                            }
                        },
                        "40MHZ": {
                            "2X2": {
                                "UL": 162.5,
                                "DL": 162.5
                            }
                        }
                    }
                },
                "11AX": {
                    "WPA2": {
                        "20MHZ": {
                            "2X2": {
                                "UL": 162.5,
                                "DL": 162.5
                            }
                        },
                        "40MHZ": {
                            "2X2": {
                                "UL": 239,
                                "DL": 239
                            }
                        }
                    }
                }
            },
            "PCIE": {
                "11N": {
                    "WPA2": {
                        "20MHZ": {
                            "2X2": {
                                "UL": 85.5,
                                "DL": 85.5
                            }
                        },
                        "40MHZ": {
                            "2X2": {
                                "UL": 162.5,
                                "DL": 162.5
                            }
                        }
                    }
                },
                "11AX": {
                    "WPA2": {
                        "20MHZ": {
                            "2X2": {
                                "UL": 162.5,
                                "DL": 162.5
                            }
                        },
                        "40MHZ": {
                            "2X2": {
                                "UL": 325,
                                "DL": 325
                            }
                        }
                    }
                }
            }
        },
        "5G": {
            "SDIO": {
                "11AC": {
                    "WPA2": {
                        "80MHZ": {
                            "2X2": {
                                "UL": 456,
                                "DL": 456
                            }
                        }
                    }
                },
                "11AX": {
                    "WPA2": {
                        "80MHZ": {
                            "2X2": {
                                "UL": 456,
                                "DL": 456
                            }
                        }
                    }
                }
            },
            "USB": {
                "11AC": {
                    "WPA2": {
                        "80MHZ": {
                            "2X2": {
                                "UL": 266,
                                "DL": 266
                            }
                        }
                    }
                },
                "11AX": {
                    "WPA2": {
                        "80MHZ": {
                            "2X2": {
                                "UL": 266,
                                "DL": 266
                            }
                        }
                    }
                }
            },
            "PCIE": {
                "11AC": {
                    "WPA2": {
                        "80MHZ": {
                            "2X2": {
                                "UL": 570,
                                "DL": 570
                            }
                        }
                    }
                },
                "11AX": {
                    "WPA2": {
                        "80MHZ": {
                            "2X2": {
                                "UL": 712.5,
                                "DL": 712.5
                            }
                        }
                    }
                }
            }
        }
    },
    "W2L": {
        "2.4G": {
            "SDIO": {
                "11N": {
                    "WPA2": {
                        "20MHZ": {
                            "2X2": {
                                "UL": 85.5,
                                "DL": 85.5
                            }
                        },
                        "40MHZ": {
                            "2X2": {
                                "UL": 162.5,
                                "DL": 162.5
                            }
                        }
                    }
                },
                "11AX": {
                    "WPA2": {
                        "20MHZ": {
                            "2X2": {
                                "UL": 162.5,
                                "DL": 162.5
                            }
                        },
                        "40MHZ": {
                            "2X2": {
                                "UL": 325,
                                "DL": 325
                            }
                        }
                    }
                }
            },
            "USB": {
                "11N": {
                    "WPA2": {
                        "20MHZ": {
                            "2X2": {
                                "UL": 85.5,
                                "DL": 85.5
                            }
                        },
                        "40MHZ": {
                            "2X2": {
                                "UL": 162.5,
                                "DL": 162.5
                            }
                        }
                    }
                },
                "11AX": {
                    "WPA2": {
                        "20MHZ": {
                            "2X2": {
                                "UL": 162.5,
                                "DL": 162.5
                            }
                        },
                        "40MHZ": {
                            "2X2": {
                                "UL": 239,
                                "DL": 239
                            }
                        }
                    }
                }
            }
        },
        "5G": {
            "SDIO": {
                "11AC": {
                    "WPA2": {
                        "80MHZ": {
                            "2X2": {
                                "UL": 456,
                                "DL": 456
                            }
                        }
                    }
                },
                "11AX": {
                    "WPA2": {
                        "80MHZ": {
                            "2X2": {
                                "UL": 475,
                                "DL": 503.5
                            }
                        }
                    }
                }
            },
            "USB": {
                "11AC": {
                    "WPA2": {
                        "80MHZ": {
                            "2X2": {
                                "UL": 266,
                                "DL": 266
                            }
                        }
                    }
                },
                "11AX": {
                    "WPA2": {
                        "80MHZ": {
                            "2X2": {
                                "UL": 266,
                                "DL": 266
                            }
                        }
                    }
                }
            }
        }
    }
}